odoo8_addon_web_widget_mail_send_odoo-8.0.1.0.0.99.dev27-py2.7-nspkg.pth
odoo8_addon_web_widget_mail_send_odoo-8.0.1.0.0.99.dev27.dist-info/DESCRIPTION.rst
odoo8_addon_web_widget_mail_send_odoo-8.0.1.0.0.99.dev27.dist-info/METADATA
odoo8_addon_web_widget_mail_send_odoo-8.0.1.0.0.99.dev27.dist-info/RECORD
odoo8_addon_web_widget_mail_send_odoo-8.0.1.0.0.99.dev27.dist-info/WHEEL
odoo8_addon_web_widget_mail_send_odoo-8.0.1.0.0.99.dev27.dist-info/metadata.json
odoo8_addon_web_widget_mail_send_odoo-8.0.1.0.0.99.dev27.dist-info/namespace_packages.txt
odoo8_addon_web_widget_mail_send_odoo-8.0.1.0.0.99.dev27.dist-info/top_level.txt
odoo_addons/web_widget_mail_send_odoo/README.rst
odoo_addons/web_widget_mail_send_odoo/__init__.py
odoo_addons/web_widget_mail_send_odoo/__openerp__.py
odoo_addons/web_widget_mail_send_odoo/assets.xml
odoo_addons/web_widget_mail_send_odoo/i18n/ca.po
odoo_addons/web_widget_mail_send_odoo/i18n/de.po
odoo_addons/web_widget_mail_send_odoo/i18n/es.po
odoo_addons/web_widget_mail_send_odoo/i18n/fi.po
odoo_addons/web_widget_mail_send_odoo/i18n/fr.po
odoo_addons/web_widget_mail_send_odoo/i18n/it.po
odoo_addons/web_widget_mail_send_odoo/i18n/pt_BR.po
odoo_addons/web_widget_mail_send_odoo/i18n/sl.po
odoo_addons/web_widget_mail_send_odoo/i18n/tr.po
odoo_addons/web_widget_mail_send_odoo/i18n/web_widget_mail_send_odoo.pot
odoo_addons/web_widget_mail_send_odoo/static/description/icon.png
odoo_addons/web_widget_mail_send_odoo/static/src/css/web_widget_mail_send_odoo.css
odoo_addons/web_widget_mail_send_odoo/static/src/js/web_widget_mail_send_odoo.js
odoo_addons/web_widget_mail_send_odoo/static/src/xml/web_widget_mail_send_odoo.xml
